gameinvasion3-1.1.23.dist-info/licenses/LICENSE
invasionEngine/__init__.py
invasionEngine/components.py
invasionEngine/constants.py
invasionEngine/events.py
invasionEngine/game_objects.py
invasionEngine/scenes.py
invasionEngine/utils.py
invasion_game_demo/__init__.py
invasion_game_demo/demo_components.py
invasion_game_demo/demo_gos.py
invasion_game_demo/demo_scenes.py
invasion_game_demo/main.py
invasion_game_demo/resources/astorid/astorid1.png
invasion_game_demo/resources/autocannon/Autocannon_Shot_1.wav
invasion_game_demo/resources/autocannon/Autocannon_Shot_2.wav
invasion_game_demo/resources/autocannon/Autocannon_Shot_3.wav
invasion_game_demo/resources/autocannon/bullet3.png
invasion_game_demo/resources/big_ship/enemy1_n2.png
invasion_game_demo/resources/big_ship/enemy2.png
invasion_game_demo/resources/big_ship/enemy3_hit.png
invasion_game_demo/resources/bo2/gif1.png
invasion_game_demo/resources/bo2/gif10.png
invasion_game_demo/resources/bo2/gif11.png
invasion_game_demo/resources/bo2/gif12.png
invasion_game_demo/resources/bo2/gif13.png
invasion_game_demo/resources/bo2/gif14.png
invasion_game_demo/resources/bo2/gif15.png
invasion_game_demo/resources/bo2/gif16.png
invasion_game_demo/resources/bo2/gif17.png
invasion_game_demo/resources/bo2/gif18.png
invasion_game_demo/resources/bo2/gif19.png
invasion_game_demo/resources/bo2/gif2.png
invasion_game_demo/resources/bo2/gif20.png
invasion_game_demo/resources/bo2/gif21.png
invasion_game_demo/resources/bo2/gif22.png
invasion_game_demo/resources/bo2/gif23.png
invasion_game_demo/resources/bo2/gif24.png
invasion_game_demo/resources/bo2/gif25.png
invasion_game_demo/resources/bo2/gif26.png
invasion_game_demo/resources/bo2/gif27.png
invasion_game_demo/resources/bo2/gif28.png
invasion_game_demo/resources/bo2/gif29.png
invasion_game_demo/resources/bo2/gif3.png
invasion_game_demo/resources/bo2/gif30.png
invasion_game_demo/resources/bo2/gif31.png
invasion_game_demo/resources/bo2/gif32.png
invasion_game_demo/resources/bo2/gif33.png
invasion_game_demo/resources/bo2/gif34.png
gameinvasion3-1.1.23.dist-info/METADATA
gameinvasion3-1.1.23.dist-info/WHEEL
gameinvasion3-1.1.23.dist-info/entry_points.txt
gameinvasion3-1.1.23.dist-info/top_level.txt
gameinvasion3-1.1.23.dist-info/RECORD
